anti_clustering/__init__.py
anti_clustering/_base.py
anti_clustering/_cluster_swap_heuristic.py
anti_clustering/_union_find.py
anti_clustering/_version.py
anti_clustering/exact_cluster_editing.py
anti_clustering/exchange_heuristic.py
anti_clustering/naive_random_heuristic.py
anti_clustering/simulated_annealing_heuristic.py
anti_clustering/tabu_search_heuristic.py
anti_clustering-0.4.1.dist-info/LICENSE
anti_clustering-0.4.1.dist-info/METADATA
anti_clustering-0.4.1.dist-info/WHEEL
anti_clustering-0.4.1.dist-info/RECORD
