Metadata-Version: 2.3
Name: anti-clustering
Version: 0.4.1
Summary: Generic Anti-Clustering Algorithm for Creating Maximally Diverse Clusters
License: Apache-2.0
Author: Matthias Als
Author-email: mata@ecco.com
Requires-Python: >=3.8
Classifier: License :: OSI Approved :: Apache Software License
Classifier: Programming Language :: Python :: 3
Classifier: Programming Language :: Python :: 3.8
Classifier: Programming Language :: Python :: 3.9
Classifier: Programming Language :: Python :: 3.10
Classifier: Programming Language :: Python :: 3.11
Classifier: Programming Language :: Python :: 3.12
Classifier: Programming Language :: Python :: 3.13
Requires-Dist: numpy (>=1.23.1,<2.0.0)
Requires-Dist: ortools (>=9.6,<10.0)
Requires-Dist: pandas (>=2.0.0,<3.0.0)
Requires-Dist: scikit-learn (>=1.1.1,<2.0.0)
Requires-Dist: scipy (>=1.9.0,<2.0.0)
Project-URL: Repository, https://github.com/SneaksAndData/anti-clustering
